google_datacatalog_redshift_connector-0.9.0-py3.8-nspkg.pth
google/datacatalog_connectors/redshift/__init__.py
google/datacatalog_connectors/redshift/datacatalog_cli.py
google/datacatalog_connectors/redshift/config/__init__.py
google/datacatalog_connectors/redshift/config/metadata_query.sql
google_datacatalog_redshift_connector-0.9.0.dist-info/METADATA
google_datacatalog_redshift_connector-0.9.0.dist-info/WHEEL
google_datacatalog_redshift_connector-0.9.0.dist-info/entry_points.txt
google_datacatalog_redshift_connector-0.9.0.dist-info/namespace_packages.txt
google_datacatalog_redshift_connector-0.9.0.dist-info/top_level.txt
google_datacatalog_redshift_connector-0.9.0.dist-info/RECORD
