Metadata-Version: 2.1
Name: google-datacatalog-redshift-connector
Version: 0.9.0
Summary: Library for ingesting Redshift metadata into Google Cloud Data Catalog
Home-page: UNKNOWN
Author: Google LLC
License: UNKNOWN
Platform: Posix; MacOS X; Windows
Classifier: Development Status :: 4 - Beta
Classifier: Programming Language :: Python :: 3.7
Requires-Dist: google-datacatalog-postgresql-connector (>=0.10.0<0.11.0)
